openspace_rvdata/__init__.py
openspace_rvdata/r2r2df.py
openspace_rvdata/tracks.py
openspace_rvdata-0.0.1.dist-info/licenses/LICENSE
openspace_rvdata-0.0.1.dist-info/METADATA
openspace_rvdata-0.0.1.dist-info/WHEEL
openspace_rvdata-0.0.1.dist-info/top_level.txt
openspace_rvdata-0.0.1.dist-info/RECORD
