Metadata-Version: 2.4
Name: openspace_rvdata
Version: 0.0.1
Summary: Library for generating OpenSpace assets for RV ship trails.
Maintainer-email: "Kristina V. Collins" <kvcollins@spacescience.org>
License: MIT License
Project-URL: source, https://github.com/KCollins/openspace_rvdata
Project-URL: documentation, https://openspace_rvdata.readthedocs.io/en/latest
Project-URL: download, https://github.com/KCollins/openspace_rvdata/releases
Keywords: OpenSpace,R2R,rvdata,research vessel,marine,cruise,lua,coordinates,observations,models,analysis,instruments,mapping,visualization,plotting,Antarctica
Classifier: Development Status :: 3 - Alpha
Classifier: Intended Audience :: Science/Research
Classifier: Topic :: Scientific/Engineering :: Oceanography
Classifier: License :: OSI Approved :: MIT License
Classifier: Natural Language :: English
Classifier: Programming Language :: Python
Classifier: Programming Language :: Python :: 3
Classifier: Programming Language :: Python :: 3.9
Requires-Python: >=3.9
License-File: LICENSE
Requires-Dist: datetime
Requires-Dist: pandas
Requires-Dist: plotly
Requires-Dist: requests
Provides-Extra: test
Requires-Dist: coverage[toml]; extra == "test"
Requires-Dist: pylint; extra == "test"
Dynamic: license-file
